README.md
setup.py
Conduit/__init__.py
Conduit/maniphest.py
Conduit/project.py
Conduit/user.py
Pycurl_Phabricator.egg-info/PKG-INFO
Pycurl_Phabricator.egg-info/SOURCES.txt
Pycurl_Phabricator.egg-info/dependency_links.txt
Pycurl_Phabricator.egg-info/requires.txt
Pycurl_Phabricator.egg-info/top_level.txt