Metadata-Version: 2.1
Name: Pycurl-Phabricator
Version: 0.2.2
Summary: Pycurl based Phabricator API library
Home-page: https://github.com/Cuile/pycurl_Phabricator
Author: Cuile
Author-email: i@cuile.com
License: UNKNOWN
Keywords: phabricator python pycurl
Platform: UNKNOWN
